story_analyzer/__init__.py
story_analyzer/archiver.py
story_analyzer/book.py
story_analyzer/data/spacy_models
story_analyzer/get_book.py
story_analyzer/main.py
story_analyzer/out.json
story_analyzer/parser_models.py
story_analyzer/spacy_queries.py
story_analyzer/tests/__init__.py
story_analyzer/tests/test_archiver.py
story_analyzer/tests/test_spacy_queries.py
story_analyzer-0.1.3.dist-info/LICENSE
story_analyzer-0.1.3.dist-info/METADATA
story_analyzer-0.1.3.dist-info/WHEEL
story_analyzer-0.1.3.dist-info/entry_points.txt
story_analyzer-0.1.3.dist-info/RECORD
