Metadata-Version: 2.1
Name: story-analyzer
Version: 0.1.3
Summary: 
License: MIT
Author: Francisco Alexandre Neves
Author-email: pg50375@alunos.uminho.pt
Requires-Python: >=3.10,<4.0
Classifier: License :: OSI Approved :: MIT License
Classifier: Programming Language :: Python :: 3
Classifier: Programming Language :: Python :: 3.10
Classifier: Programming Language :: Python :: 3.11
Requires-Dist: beautifulsoup4 (>=4.12.2,<5.0.0)
Requires-Dist: colorama (>=0.4.6,<0.5.0)
Requires-Dist: gensim (>=4.3.1,<5.0.0)
Requires-Dist: sentencepiece (>=0.1.97,<0.2.0)
Requires-Dist: sortedcontainers (>=2.4.0,<3.0.0)
Requires-Dist: spacy (>=3.5.1,<4.0.0)
Requires-Dist: torch (>=2.0.0,<3.0.0)
Requires-Dist: transformers (>=4.27.4,<5.0.0)
